{"lace": "dantelă", "chain": "lanţ", "money": "cu privire la bani", "paper": "de hârtie", "radio": "radio", "shoe": "pantof", "keyboard": "orgă electronică", "chair": "scaun", "milk": "lapte", "thermostat": "termostat", "clipper": "avion de pasageri (transoceanic)", "lampshade": "abajur", "sandal": "sanda", "monitor": "cameră de supraveghere", "tire": "pneu", "cup": "ceşcuţă", "tv": "televizor", "peanut": "alună-americană/arahidă", "backpack": "rucsac", "drive": "de transmisie", "jar": "borcan", "window": "fereastră", "tape": "bandă magnetică", "photo": "fotografie", "pad": "bloc de foi", "piano": "de pian", "carton": "cutie de carton (de dimensiuni mici)", "sauce": "sos", "stop sign": "stop (semn de circulaţie)", "plate": "farfurie", "cube": "cub", "food": "alimentar", "blanket": "cuvertură (dintr-o pânză/dintr-un material textil), pătură (mai ales de lână)", "mop": "mop", "stop": "de oprire", "fridge": "frigider", "vase": "vază", "band": "trupă (de rock)", "spoon": "lingură", "grid": "grilaj", "outlet": "gura unei conducte (de gaz, aer, apă)", "desk": "birou", "press": "(aclamare, libertate) a presei", "towel": "prosop", "bread": "de pâine", "lip gloss": "luciu de buze", "sofa": "canapea", "button": "nasture (la haină), buton (al unui aparat/întrerupător electric)", "bracelet": "brăţară", "greeting": "salutare", "candy": "dulciuri sau ciocolată", "perfume": "parfum", "magnet": "magnet", "bag": "sac", "sand": "nisip", "sponge": "burete", "clay": "argilă", "sidewalk": "trotuar", "tray": "tavă", "glasses": "ochelari", "picture frame": "cadru (al unui tablou, al unei fotografii)", "sketch": "schiţă", "hanger": "umeraş", "doll": "păpuşă", "house": "casă", "frame": "structură (a unei clădiri), osatură (a unui vas), şarpantă (cu referire la acoperiş)", "duck": "raţă", "packet": "pachet", "seat": "loc", "hair": "(claie de) păr", "computer": "computer sau calculator electronic", "video": "(companie producătoare) de casete video", "mirror": "oglindă", "candle": "lumânare", "air": "aerian", "canvas": "pânză tare şi groasă", "flower": "floare", "tissue": "ţesut", "clock": "ceas, orologiu", "sun": "soare", "water bottle": "bidon", "ice": "gheaţă", "cell": "celulă (în care este închis un prizonier)", "pen": "stilou", "machine": "maşină", "knife": "cuţit", "pants": "pantaloni", "leg": "picior", "tree": "copac", "rug": "covoraş", "cork": "plută", "toothbrush": "periuţă de dinţi", "packing": "ambalaj", "cookie": "prăjitură de casă", "web": "reţeaua World Wide Web", "key": "cheie", "lotion": "loţiune", "card": "vedere (expediată dintr-o excursie), felicitare (expediată cu prilejul unei aniversări)", "nail file": "pilă de unghii", "chapter": "capitol", "water": "cu apă", "thread": "fir", "headphones": "căşti", "bow": "plecăciune", "credit": "merit", "games": "sport", "menu": "meniu", "soda": "carbonat/bicarbonat de sodiu", "credit card": "carte de credit", "cinder": "cărbune aprins", "clothes": "(coş) pentru rufe", "pillow": "pernă", "block": "bloc", "clamp": "şurub de strângere", "ballpoint": "pix", "shovel": "lopată", "apple": "de mere", "pot": "oală", "speaker": "vorbitor", "slipper": "papuc de casă", "brush": "perie", "puddle": "băltoacă", "fake": "fals", "table": "masă", "ring": "cerc", "belt": "centură", "eye": "la ochi", "bookmark": "semn de carte", "toothpaste": "pastă de dinţi", "gloss": "lustru", "wrapper": "hârtie de împachetat", "plastic": "material plastic", "paint": "vopsea", "photo album": "album de fotografii", "camera": "aparat foto", "checkbook": "carnet de cecuri", "spring": "primăvară", "drumstick": "baghetă pentru tobă", "white": "culoare albă", "banana": "banană", "toe": "deget de la picior", "fork": "furculiţă", "box": "cutiuţă (de carton)", "door": "al uşii", "eraser": "gumă de şters", "shawl": "şal", "needle": "ac", "CD": "compact disc", "glass": "sticlă", "flag": "drapel", "stick": "băţ", "sign": "semn", "nail": "unghie", "television": "(transmisie) la televizor", "player": "(sport) jucător", "car": "auto", "cap": "şapcă", "shampoo": "şampon", "bed": "licenţiat în pedagogie", "cat": "pisică (domestică)", "chalk": "în cretă", "wallet": "portofel", "note": "notă", "street": "stradă", "rubber band": "elastic", "can": "conservă (cutie de conserve)", "drill": "bormaşină", "newspaper": "dintr-un ziar", "playing card": "carte de joc", "toilet": "toaletă", "USB": "USB, magistrală serială universală", "pencil": "creion", "deodorant": "deodorant", "purse": "poşetă", "site": "teren de construcţii", "sticky": "lipicios", "drawer": "sertar", "carrot": "morcov (propr.)", "file": "dosar", "conditioner": "balsam pentru păr", "tooth": "dinte", "mouse": "(propr., fig.) şoarece", "helmet": "cască", "shirt": "cămaşă", "floor": "parchet", "sailboat": "barcă cu pânze", "balloon": "balon", "bowl": "bol", "couch": "canapea", "rubber": "cauciuc", "lamp": "lampă", "book": "carte", "lip": "buză", "boom": "în plină dezvoltare", "thermometer": "termometru", "tie": "cravată", "soap": "săpun", "picture": "tablou", "screw": "şurub", "watch": "ceas", "swing": "mişcare de oscilaţie", "controller": "director", "washing": "spălare", "chocolate": "ciocolată", "pool": "iaz", "glow": "incandescenţă", "tomato": "de roşii", "phone": "telefon", "washing machine": "maşină de spălat", "liner": "vas de linie", "face": "faţă", "truck": "camion", "bottle": "sticlă", "telephone": "telefon", "model": "machetă", "scotch": "whisky scoţian", "playing": "interpretare"}